cldflex/__init__.py
cldflex/cldf.py
cldflex/cli.py
cldflex/flex2csv.py
cldflex/helpers.py
cldflex/lift2csv.py
cldflex-0.1.1.dist-info/LICENSE
cldflex-0.1.1.dist-info/METADATA
cldflex-0.1.1.dist-info/WHEEL
cldflex-0.1.1.dist-info/entry_points.txt
cldflex-0.1.1.dist-info/RECORD
