Metadata-Version: 2.1
Name: cldflex
Version: 0.1.1
Summary: Convert FLEx data to CLDF-ready CSV.
Home-page: https://fl.mt/cldflex
License: Apache-2.0
Author: Florian Matter
Author-email: flmt@mailbox.org
Requires-Python: >=3.8.1,<4.0.0
Classifier: Development Status :: 4 - Beta
Classifier: Intended Audience :: Science/Research
Classifier: License :: OSI Approved :: Apache Software License
Classifier: Natural Language :: English
Classifier: Programming Language :: Python :: 3
Classifier: Programming Language :: Python :: 3.9
Classifier: Programming Language :: Python :: 3.10
Classifier: Programming Language :: Python :: 3.11
Classifier: Programming Language :: Python :: 3.12
Classifier: Programming Language :: Python :: 3.8
Requires-Dist: beautifulsoup4 (>=4.12.2,<5.0.0)
Requires-Dist: cldf-ldd (>=0.0.6,<0.0.7)
Requires-Dist: cldfbench (>=1.14.0,<2.0.0)
Requires-Dist: clldutils (>=3.20.0,<4.0.0)
Requires-Dist: colorlog (>=6.7.0,<7.0.0)
Requires-Dist: humidifier (>=0.0.2,<0.0.3)
Requires-Dist: morphinder (>=0.0.2,<0.0.3)
Requires-Dist: pytest (>=7.4.2,<8.0.0)
Project-URL: Bug tracker, https://github.com/fmatter/cldflex/issues
Project-URL: Repository, https://github.com/fmatter/cldflex
